{"time": "2021/02/01 00:00:03","temperature": "12.25","humidity": "44.41"}
{"time": "2021/02/01 00:15:02","temperature": "12.02","humidity": "44.11"}
{"time": "2021/02/01 00:30:03","temperature": "11.77","humidity": "44.00"}
{"time": "2021/02/01 00:45:03","temperature": "11.59","humidity": "43.81"}
{"time": "2021/02/01 01:00:03","temperature": "11.29","humidity": "43.56"}
{"time": "2021/02/01 01:15:02","temperature": "11.04","humidity": "43.62"}
{"time": "2021/02/01 01:30:03","temperature": "10.82","humidity": "43.36"}
{"time": "2021/02/01 01:45:03","temperature": "10.60","humidity": "43.23"}
{"time": "2021/02/01 02:00:03","temperature": "10.32","humidity": "43.06"}
{"time": "2021/02/01 02:15:03","temperature": "10.21","humidity": "42.99"}
{"time": "2021/02/01 02:30:03","temperature": "9.97","humidity": "42.98"}
{"time": "2021/02/01 02:45:03","temperature": "9.88","humidity": "42.91"}
{"time": "2021/02/01 03:00:03","temperature": "9.64","humidity": "42.69"}
{"time": "2021/02/01 03:15:03","temperature": "9.45","humidity": "42.64"}
{"time": "2021/02/01 03:30:03","temperature": "9.28","humidity": "42.50"}
{"time": "2021/02/01 03:45:03","temperature": "9.08","humidity": "42.33"}
{"time": "2021/02/01 04:00:03","temperature": "8.91","humidity": "42.41"}
{"time": "2021/02/01 04:15:03","temperature": "8.69","humidity": "42.44"}
{"time": "2021/02/01 04:30:02","temperature": "8.50","humidity": "42.18"}
{"time": "2021/02/01 04:45:03","temperature": "8.32","humidity": "42.19"}
{"time": "2021/02/01 05:00:03","temperature": "8.19","humidity": "42.08"}
{"time": "2021/02/01 05:15:03","temperature": "7.94","humidity": "42.08"}
{"time": "2021/02/01 05:30:02","temperature": "7.93","humidity": "42.10"}
{"time": "2021/02/01 05:45:02","temperature": "7.67","humidity": "41.80"}
{"time": "2021/02/01 06:00:03","temperature": "7.64","humidity": "41.87"}
{"time": "2021/02/01 06:15:03","temperature": "7.52","humidity": "43.47"}
{"time": "2021/02/01 06:30:02","temperature": "7.62","humidity": "51.85"}
{"time": "2021/02/01 06:45:03","temperature": "7.94","humidity": "51.64"}
{"time": "2021/02/01 07:00:02","temperature": "8.66","humidity": "50.45"}
{"time": "2021/02/01 07:15:03","temperature": "9.26","humidity": "48.79"}
{"time": "2021/02/01 07:30:02","temperature": "9.39","humidity": "50.04"}
{"time": "2021/02/01 07:45:02","temperature": "9.59","humidity": "48.65"}
{"time": "2021/02/01 08:00:03","temperature": "9.46","humidity": "47.89"}
{"time": "2021/02/01 08:15:02","temperature": "9.33","humidity": "47.76"}
{"time": "2021/02/01 08:30:03","temperature": "9.32","humidity": "47.57"}
{"time": "2021/02/01 08:45:03","temperature": "9.22","humidity": "47.23"}
{"time": "2021/02/01 09:00:02","temperature": "9.18","humidity": "47.14"}
{"time": "2021/02/01 09:15:03","temperature": "9.11","humidity": "47.17"}
{"time": "2021/02/01 09:30:03","temperature": "9.00","humidity": "46.82"}
{"time": "2021/02/01 09:45:03","temperature": "8.88","humidity": "47.12"}
{"time": "2021/02/01 10:00:03","temperature": "8.87","humidity": "47.45"}
{"time": "2021/02/01 10:15:03","temperature": "8.63","humidity": "49.33"}
{"time": "2021/02/01 10:30:03","temperature": "9.08","humidity": "49.32"}
{"time": "2021/02/01 10:45:03","temperature": "9.26","humidity": "51.07"}
{"time": "2021/02/01 11:00:03","temperature": "9.70","humidity": "58.36"}
{"time": "2021/02/01 11:15:03","temperature": "10.05","humidity": "58.21"}
{"time": "2021/02/01 11:30:03","temperature": "10.97","humidity": "54.18"}
{"time": "2021/02/01 11:45:03","temperature": "11.50","humidity": "51.17"}
{"time": "2021/02/01 12:00:03","temperature": "11.80","humidity": "49.66"}
{"time": "2021/02/01 12:15:03","temperature": "12.14","humidity": "48.19"}
{"time": "2021/02/01 12:30:03","temperature": "12.14","humidity": "47.36"}
{"time": "2021/02/01 12:45:03","temperature": "12.38","humidity": "46.46"}
{"time": "2021/02/01 13:00:03","temperature": "12.42","humidity": "45.76"}
{"time": "2021/02/01 13:15:03","temperature": "12.33","humidity": "45.34"}
{"time": "2021/02/01 13:30:03","temperature": "12.32","humidity": "44.60"}
{"time": "2021/02/01 13:45:03","temperature": "12.14","humidity": "43.93"}
{"time": "2021/02/01 14:00:03","temperature": "12.01","humidity": "43.83"}
{"time": "2021/02/01 14:15:03","temperature": "11.97","humidity": "43.70"}
{"time": "2021/02/01 14:30:03","temperature": "11.94","humidity": "44.37"}
{"time": "2021/02/01 14:45:03","temperature": "11.69","humidity": "44.80"}
{"time": "2021/02/01 15:00:03","temperature": "11.97","humidity": "44.19"}
{"time": "2021/02/01 15:15:03","temperature": "12.49","humidity": "43.61"}
{"time": "2021/02/01 15:30:02","temperature": "12.94","humidity": "42.62"}
{"time": "2021/02/01 15:45:02","temperature": "13.36","humidity": "42.08"}
{"time": "2021/02/01 16:00:02","temperature": "13.91","humidity": "40.86"}
{"time": "2021/02/01 16:15:02","temperature": "14.48","humidity": "39.65"}
{"time": "2021/02/01 16:30:03","temperature": "14.83","humidity": "39.24"}
{"time": "2021/02/01 16:45:03","temperature": "15.03","humidity": "39.08"}
{"time": "2021/02/01 17:00:02","temperature": "15.32","humidity": "38.67"}
{"time": "2021/02/01 17:15:02","temperature": "15.53","humidity": "39.11"}
{"time": "2021/02/01 17:30:03","temperature": "15.83","humidity": "38.85"}
{"time": "2021/02/01 17:45:03","temperature": "15.94","humidity": "39.03"}
{"time": "2021/02/01 18:00:03","temperature": "16.36","humidity": "38.48"}
{"time": "2021/02/01 18:15:03","temperature": "16.60","humidity": "38.65"}
{"time": "2021/02/01 18:30:03","temperature": "16.72","humidity": "38.60"}
{"time": "2021/02/01 18:45:03","temperature": "16.94","humidity": "39.71"}
{"time": "2021/02/01 19:00:03","temperature": "17.06","humidity": "39.66"}
{"time": "2021/02/01 19:15:03","temperature": "17.15","humidity": "40.72"}
{"time": "2021/02/01 19:30:03","temperature": "17.03","humidity": "42.61"}
{"time": "2021/02/01 19:45:03","temperature": "16.63","humidity": "43.59"}
{"time": "2021/02/01 20:00:03","temperature": "16.25","humidity": "44.32"}
{"time": "2021/02/01 20:15:03","temperature": "15.93","humidity": "44.90"}
{"time": "2021/02/01 20:30:02","temperature": "15.69","humidity": "47.47"}
{"time": "2021/02/01 20:45:02","temperature": "15.28","humidity": "50.93"}
{"time": "2021/02/01 21:00:02","temperature": "15.22","humidity": "49.18"}
{"time": "2021/02/01 21:15:03","temperature": "15.10","humidity": "51.60"}
{"time": "2021/02/01 21:30:03","temperature": "14.84","humidity": "52.35"}
{"time": "2021/02/01 21:45:03","temperature": "14.86","humidity": "51.69"}
{"time": "2021/02/01 22:00:03","temperature": "14.35","humidity": "51.30"}
{"time": "2021/02/01 22:15:03","temperature": "14.29","humidity": "50.81"}
{"time": "2021/02/01 22:30:03","temperature": "13.98","humidity": "49.96"}
{"time": "2021/02/01 22:45:03","temperature": "13.84","humidity": "49.61"}
{"time": "2021/02/01 23:00:03","temperature": "13.72","humidity": "49.16"}
{"time": "2021/02/01 23:15:03","temperature": "13.57","humidity": "48.97"}
{"time": "2021/02/01 23:30:03","temperature": "13.53","humidity": "48.77"}
{"time": "2021/02/01 23:45:03","temperature": "13.49","humidity": "48.58"}
{"time": "2021/02/02 00:00:04","temperature": "13.35","humidity": "48.56"}
{"time": "2021/02/02 00:15:03","temperature": "13.15","humidity": "48.42"}
{"time": "2021/02/02 00:30:02","temperature": "13.15","humidity": "48.28"}
{"time": "2021/02/02 00:45:02","temperature": "12.94","humidity": "48.48"}
{"time": "2021/02/02 01:00:03","temperature": "12.91","humidity": "48.60"}
{"time": "2021/02/02 01:15:03","temperature": "12.74","humidity": "48.51"}
{"time": "2021/02/02 01:30:02","temperature": "12.70","humidity": "48.46"}
{"time": "2021/02/02 01:45:02","temperature": "12.70","humidity": "48.29"}
{"time": "2021/02/02 02:00:03","temperature": "12.62","humidity": "48.26"}
{"time": "2021/02/02 02:15:02","temperature": "12.55","humidity": "48.31"}
{"time": "2021/02/02 02:30:03","temperature": "12.42","humidity": "48.17"}
{"time": "2021/02/02 02:45:03","temperature": "12.35","humidity": "48.17"}
{"time": "2021/02/02 03:00:03","temperature": "12.33","humidity": "48.14"}
{"time": "2021/02/02 03:15:03","temperature": "12.38","humidity": "48.05"}
{"time": "2021/02/02 03:30:03","temperature": "12.18","humidity": "48.04"}
{"time": "2021/02/02 03:45:03","temperature": "12.09","humidity": "48.00"}
{"time": "2021/02/02 04:00:03","temperature": "12.11","humidity": "48.04"}
{"time": "2021/02/02 04:15:03","temperature": "12.00","humidity": "47.82"}
{"time": "2021/02/02 04:30:02","temperature": "11.95","humidity": "47.76"}
{"time": "2021/02/02 04:45:03","temperature": "11.91","humidity": "47.73"}
{"time": "2021/02/02 05:00:03","temperature": "11.73","humidity": "47.68"}
{"time": "2021/02/02 05:15:03","temperature": "11.72","humidity": "47.38"}
{"time": "2021/02/02 05:30:03","temperature": "11.50","humidity": "47.53"}
{"time": "2021/02/02 05:45:03","temperature": "11.52","humidity": "47.31"}
{"time": "2021/02/02 06:00:03","temperature": "11.46","humidity": "47.35"}
{"time": "2021/02/02 06:15:03","temperature": "11.34","humidity": "47.94"}
{"time": "2021/02/02 06:30:03","temperature": "11.90","humidity": "50.87"}
{"time": "2021/02/02 06:45:03","temperature": "12.66","humidity": "51.62"}
{"time": "2021/02/02 07:00:03","temperature": "13.41","humidity": "50.08"}
{"time": "2021/02/02 07:15:03","temperature": "13.94","humidity": "47.82"}
{"time": "2021/02/02 07:30:03","temperature": "14.14","humidity": "47.23"}
{"time": "2021/02/02 07:45:03","temperature": "14.21","humidity": "46.75"}
{"time": "2021/02/02 08:00:03","temperature": "14.19","humidity": "47.24"}
{"time": "2021/02/02 08:15:03","temperature": "14.05","humidity": "47.89"}
{"time": "2021/02/02 08:30:02","temperature": "14.08","humidity": "47.21"}
{"time": "2021/02/02 08:45:03","temperature": "14.02","humidity": "47.31"}
{"time": "2021/02/02 09:00:03","temperature": "14.02","humidity": "47.57"}
{"time": "2021/02/02 09:15:02","temperature": "13.90","humidity": "47.83"}
{"time": "2021/02/02 09:30:03","temperature": "13.90","humidity": "47.87"}
{"time": "2021/02/02 09:45:03","temperature": "13.74","humidity": "47.92"}
{"time": "2021/02/02 10:00:03","temperature": "13.81","humidity": "47.86"}
{"time": "2021/02/02 10:15:03","temperature": "13.86","humidity": "47.79"}
{"time": "2021/02/02 10:30:03","temperature": "13.89","humidity": "46.46"}
{"time": "2021/02/02 10:45:03","temperature": "13.94","humidity": "45.23"}
{"time": "2021/02/02 11:00:03","temperature": "14.11","humidity": "44.51"}
{"time": "2021/02/02 11:15:03","temperature": "14.35","humidity": "44.42"}
{"time": "2021/02/02 11:30:03","temperature": "14.69","humidity": "44.06"}
{"time": "2021/02/02 11:45:03","temperature": "15.25","humidity": "42.32"}
{"time": "2021/02/02 12:00:03","temperature": "15.63","humidity": "40.96"}
